ppack/__init__.py
ppack-0.0.1.dist-info/LICENSE
ppack-0.0.1.dist-info/METADATA
ppack-0.0.1.dist-info/WHEEL
ppack-0.0.1.dist-info/top_level.txt
ppack-0.0.1.dist-info/RECORD
