Metadata-Version: 2.1
Name: ppack
Version: 0.0.1
Summary: First try to write a Python package
Home-page: https://gitlab.com/kasramsh/ppack
Author: Kasra Manshaei
Author-email: kasramsh@gmail.com
License: UNKNOWN
Platform: UNKNOWN
Classifier: Programming Language :: Python :: 3
Classifier: License :: OSI Approved :: MIT License
Classifier: Operating System :: OS Independent
